sio/__init__.py
PySIO-0.1.1.dist-info/LICENSE
PySIO-0.1.1.dist-info/METADATA
PySIO-0.1.1.dist-info/WHEEL
PySIO-0.1.1.dist-info/top_level.txt
PySIO-0.1.1.dist-info/RECORD
