Metadata-Version: 2.1
Name: PySIO
Version: 0.1.1
Summary: Parser for SLAC\'s Serial Input Output file format.
Home-page: https://github.com/kkrizka/PySIO
Author: Karol Krizka
Author-email: kkrizka@gmail.com
License: UNKNOWN
Platform: UNKNOWN
Classifier: Programming Language :: Python :: 3
Classifier: License :: OSI Approved :: GNU General Public License v3 (GPLv3)
Classifier: Operating System :: OS Independent
License-File: LICENSE
